{
	"info": {
		"_postman_id": "50e4a8ed-833f-4318-9eba-7da4f892248f",
		"name": "api-rest",
		"schema": "https://schema.getpostman.com/json/collection/v2.1.0/collection.json",
		"_exporter_id": "18266506"
	},
	"item": [
		{
			"name": "create-article",
			"request": {
				"method": "POST",
				"header": [],
				"body": {
					"mode": "urlencoded",
					"urlencoded": [
						{
							"key": "title",
							"value": "Curso PHP",
							"type": "text"
						},
						{
							"key": "content",
							"value": "Contenido para convertirte en un desarrollador PHP",
							"type": "text"
						}
					]
				},
				"url": {
					"raw": "http://localhost:8080/api/create-article",
					"protocol": "http",
					"host": [
						"localhost"
					],
					"port": "8080",
					"path": [
						"api",
						"create-article"
					]
				}
			},
			"response": []
		},
		{
			"name": "get-articles",
			"protocolProfileBehavior": {
				"disableBodyPruning": true
			},
			"request": {
				"method": "GET",
				"header": [],
				"body": {
					"mode": "urlencoded",
					"urlencoded": [
						{
							"key": "title",
							"value": "Curso Wordpress",
							"type": "text"
						},
						{
							"key": "content",
							"value": "Contenido de como hace run sitio",
							"type": "text"
						}
					]
				},
				"url": {
					"raw": "http://localhost:8080/api/get-articles",
					"protocol": "http",
					"host": [
						"localhost"
					],
					"port": "8080",
					"path": [
						"api",
						"get-articles"
					]
				}
			},
			"response": []
		},
		{
			"name": "get-one-article",
			"protocolProfileBehavior": {
				"disableBodyPruning": true
			},
			"request": {
				"method": "GET",
				"header": [],
				"body": {
					"mode": "urlencoded",
					"urlencoded": [
						{
							"key": "title",
							"value": "Curso Wordpress",
							"type": "text"
						},
						{
							"key": "content",
							"value": "Contenido de como hace run sitio",
							"type": "text"
						}
					]
				},
				"url": {
					"raw": "http://localhost:8080/api/get-article/6458f4e607ecc2c7982d0bbb",
					"protocol": "http",
					"host": [
						"localhost"
					],
					"port": "8080",
					"path": [
						"api",
						"get-article",
						"6458f4e607ecc2c7982d0bbb"
					]
				}
			},
			"response": []
		},
		{
			"name": "delete-article",
			"request": {
				"method": "DELETE",
				"header": [],
				"body": {
					"mode": "urlencoded",
					"urlencoded": [
						{
							"key": "title",
							"value": "Curso Wordpress",
							"type": "text"
						},
						{
							"key": "content",
							"value": "Contenido de como hace run sitio",
							"type": "text"
						}
					]
				},
				"url": {
					"raw": "http://localhost:8080/api/get-article/64555cc43fa6f94d18e44cab",
					"protocol": "http",
					"host": [
						"localhost"
					],
					"port": "8080",
					"path": [
						"api",
						"get-article",
						"64555cc43fa6f94d18e44cab"
					]
				}
			},
			"response": []
		},
		{
			"name": "edit-article",
			"request": {
				"method": "PUT",
				"header": [],
				"body": {
					"mode": "urlencoded",
					"urlencoded": [
						{
							"key": "title",
							"value": "Curso de PHP y Java",
							"type": "text"
						},
						{
							"key": "content",
							"value": "Como ser un Backend Developer",
							"type": "text"
						}
					]
				},
				"url": {
					"raw": "http://localhost:8080/api/get-article/6458f4e607ecc2c7982d0bbb",
					"protocol": "http",
					"host": [
						"localhost"
					],
					"port": "8080",
					"path": [
						"api",
						"get-article",
						"6458f4e607ecc2c7982d0bbb"
					]
				}
			},
			"response": []
		},
		{
			"name": "upload-image",
			"request": {
				"method": "POST",
				"header": [],
				"body": {
					"mode": "formdata",
					"formdata": [
						{
							"key": "file0",
							"type": "file",
							"src": "/Users/amadeoisella/Downloads/React-icon.svg.png"
						}
					]
				},
				"url": {
					"raw": "http://localhost:8080/api/upload-image/645564b0504f42045f1d04d1",
					"protocol": "http",
					"host": [
						"localhost"
					],
					"port": "8080",
					"path": [
						"api",
						"upload-image",
						"645564b0504f42045f1d04d1"
					]
				}
			},
			"response": []
		},
		{
			"name": "get-image-format",
			"protocolProfileBehavior": {
				"disableBodyPruning": true
			},
			"request": {
				"method": "GET",
				"header": [],
				"body": {
					"mode": "formdata",
					"formdata": [
						{
							"key": "file",
							"value": "",
							"type": "text"
						}
					]
				},
				"url": {
					"raw": "http://localhost:8080/api/image/article1683562966374React-icon.svg.png",
					"protocol": "http",
					"host": [
						"localhost"
					],
					"port": "8080",
					"path": [
						"api",
						"image",
						"article1683562966374React-icon.svg.png"
					]
				}
			},
			"response": []
		},
		{
			"name": "search-engine",
			"protocolProfileBehavior": {
				"disableBodyPruning": true
			},
			"request": {
				"method": "GET",
				"header": [],
				"body": {
					"mode": "formdata",
					"formdata": [
						{
							"key": "file",
							"value": "",
							"type": "text"
						}
					]
				},
				"url": {
					"raw": "http://localhost:8080/api/search/jsx",
					"protocol": "http",
					"host": [
						"localhost"
					],
					"port": "8080",
					"path": [
						"api",
						"search",
						"jsx"
					]
				}
			},
			"response": []
		}
	]
}